{
  "/_app": "pages/_app.js",
  "/_document": "pages/_document.js",
  "/_error": "pages/_error.js",
  "/api/hello": "pages/api/hello.js",
  "/": "pages/index.html",
  "/alcaladehenares": "pages/alcaladehenares.js",
  "/alamos": "pages/alamos.js",
  "/albufera": "pages/albufera.js",
  "/alcala": "pages/alcala.js",
  "/alfonsoelsabio": "pages/alfonsoelsabio.js",
  "/alcorcon": "pages/alcorcon.js",
  "/alcobendas": "pages/alcobendas.js",
  "/almeria-tienda": "pages/almeria-tienda.js",
  "/almeria": "pages/almeria.js",
  "/alicante": "pages/alicante.js",
  "/aluche": "pages/aluche.js",
  "/antoniomarques": "pages/antoniomarques.js",
  "/ayuntamiento": "pages/ayuntamiento.js",
  "/avburjassot": "pages/avburjassot.js",
  "/barcelona": "pages/barcelona.js",
  "/bilbao": "pages/bilbao.js",
  "/avpuerto": "pages/avpuerto.js",
  "/archiduquecarlos": "pages/archiduquecarlos.js",
  "/benidorm": "pages/benidorm.js",
  "/caminosuarez": "pages/caminosuarez.js",
  "/cartagena": "pages/cartagena.js",
  "/cruzconde": "pages/cruzconde.js",
  "/cadiz": "pages/cadiz.js",
  "/castellon": "pages/castellon.js",
  "/cuatrocaminos": "pages/cuatrocaminos.js",
  "/elche": "pages/elche.js",
  "/delicias": "pages/delicias.js",
  "/elclot": "pages/elclot.js",
  "/diagonal335": "pages/diagonal335.js",
  "/granada": "pages/granada.js",
  "/getafe": "pages/getafe.js",
  "/gijon": "pages/gijon.js",
  "/floridablanca": "pages/floridablanca.js",
  "/granvia": "pages/granvia.js",
  "/hostafrancs": "pages/hostafrancs.js",
  "/jerez": "pages/jerez.js",
  "/guzmanelbueno": "pages/guzmanelbueno.js",
  "/junterones": "pages/junterones.js",
  "/laaurora": "pages/laaurora.js",
  "/logrono": "pages/logrono.js",
  "/lacoruna": "pages/lacoruna.js",
  "/leon": "pages/leon.js",
  "/madrid": "pages/madrid.js",
  "/murcia": "pages/murcia.js",
  "/malaga": "pages/malaga.js",
  "/oviedo": "pages/oviedo.js",
  "/marbella": "pages/marbella.js",
  "/nervion": "pages/nervion.js",
  "/palma": "pages/palma.js",
  "/plazaespana": "pages/plazaespana.js",
  "/puertadelangel": "pages/puertadelangel.js",
  "/plazapontevedra": "pages/plazapontevedra.js",
  "/reus": "pages/reus.js",
  "/puentezuelas": "pages/puentezuelas.js",
  "/quintana": "pages/quintana.js",
  "/sanbernardo": "pages/sanbernardo.js",
  "/roquetasdemar": "pages/roquetasdemar.js",
  "/saneloy": "pages/saneloy.js",
  "/santadria": "pages/santadria.js",
  "/sanjorge": "pages/sanjorge.js",
  "/santacruz": "pages/santacruz.js",
  "/sanfrancisco": "pages/sanfrancisco.js",
  "/santantoni": "pages/santantoni.js",
  "/santander": "pages/santander.js",
  "/santiagodecompostela": "pages/santiagodecompostela.js",
  "/tarragona": "pages/tarragona.js",
  "/sevilla": "pages/sevilla.js",
  "/sindicat": "pages/sindicat.js",
  "/tetuan": "pages/tetuan.js",
  "/tirsodemolina": "pages/tirsodemolina.js",
  "/urzaiz": "pages/urzaiz.js",
  "/usera": "pages/usera.js",
  "/valencia": "pages/valencia.js",
  "/vigo": "pages/vigo.js",
  "/valladolid": "pages/valladolid.js",
  "/zaragoza": "pages/zaragoza.js",
  "/404": "pages/404.html"
}